[
  {
    "id": "greenhouse",
    "source_name": "Greenhouse",
    "source_tier": "direct_ats",
    "adapter_type": "greenhouse",
    "supports_direct_validity_checks": true
  },
  {
    "id": "lever",
    "source_name": "Lever",
    "source_tier": "direct_ats",
    "adapter_type": "lever",
    "supports_direct_validity_checks": true
  },
  {
    "id": "ashby",
    "source_name": "Ashby",
    "source_tier": "direct_ats",
    "adapter_type": "ashby",
    "supports_direct_validity_checks": true
  },
  {
    "id": "smartrecruiters",
    "source_name": "SmartRecruiters",
    "source_tier": "direct_ats",
    "adapter_type": "smartrecruiters",
    "supports_direct_validity_checks": true
  },
  {
    "id": "pinpoint",
    "source_name": "Pinpoint",
    "source_tier": "direct_ats",
    "adapter_type": "pinpoint",
    "supports_direct_validity_checks": false
  },
  {
    "id": "welcomekit",
    "source_name": "Welcome Kit",
    "source_tier": "direct_ats",
    "adapter_type": "welcomekit",
    "supports_direct_validity_checks": false
  },
  {
    "id": "custom",
    "source_name": "Custom careers page",
    "source_tier": "direct_ats",
    "adapter_type": "custom",
    "supports_direct_validity_checks": false
  },
  {
    "id": "linkedin",
    "source_name": "LinkedIn",
    "source_tier": "curated_board",
    "adapter_type": null,
    "supports_direct_validity_checks": false
  },
  {
    "id": "we_work_remotely",
    "source_name": "We Work Remotely",
    "source_tier": "curated_board",
    "adapter_type": null,
    "supports_direct_validity_checks": false
  },
  {
    "id": "working_nomads",
    "source_name": "Working Nomads",
    "source_tier": "curated_board",
    "adapter_type": null,
    "supports_direct_validity_checks": false
  },
  {
    "id": "remote_co",
    "source_name": "Remote.co",
    "source_tier": "curated_board",
    "adapter_type": null,
    "supports_direct_validity_checks": false
  },
  {
    "id": "idealist",
    "source_name": "Idealist",
    "source_tier": "curated_board",
    "adapter_type": null,
    "supports_direct_validity_checks": false
  },
  {
    "id": "flexjobs",
    "source_name": "FlexJobs",
    "source_tier": "curated_board",
    "adapter_type": null,
    "supports_direct_validity_checks": false
  },
  {
    "id": "indeed",
    "source_name": "Indeed",
    "source_tier": "aggregator",
    "adapter_type": null,
    "supports_direct_validity_checks": false
  },
  {
    "id": "talent",
    "source_name": "Talent.com",
    "source_tier": "aggregator",
    "adapter_type": null,
    "supports_direct_validity_checks": false
  },
  {
    "id": "monster",
    "source_name": "Monster",
    "source_tier": "aggregator",
    "adapter_type": null,
    "supports_direct_validity_checks": false
  },
  {
    "id": "jooble",
    "source_name": "Jooble",
    "source_tier": "aggregator",
    "adapter_type": null,
    "supports_direct_validity_checks": false
  },
  {
    "id": "jora",
    "source_name": "Jora",
    "source_tier": "aggregator",
    "adapter_type": null,
    "supports_direct_validity_checks": false
  },
  {
    "id": "lensa",
    "source_name": "Lensa",
    "source_tier": "aggregator",
    "adapter_type": null,
    "supports_direct_validity_checks": false
  },
  {
    "id": "ziprecruiter",
    "source_name": "ZipRecruiter",
    "source_tier": "aggregator",
    "adapter_type": null,
    "supports_direct_validity_checks": false
  }
]
